genome_downloader/__init__.py
genome_downloader/__main__.py
genome_downloader/download.py
genome_downloader/gff_longest_transcript.py
genome_downloader-0.0.6.dist-info/METADATA
genome_downloader-0.0.6.dist-info/WHEEL
genome_downloader-0.0.6.dist-info/top_level.txt
genome_downloader-0.0.6.dist-info/RECORD
