Metadata-Version: 2.1
Name: genome-downloader
Version: 0.0.6
Summary: A package to download genome, annotations and bowtie2 indexes
Author-email: Sergej Andrejev <sandrejev@gmail.com>
Project-URL: repository, https://github.com/brainbreaks/genome_downloader
Keywords: genomics,bioinformatics
Requires-Python: >=3.8
Requires-Dist: requests (>=2)
Requires-Dist: httplib2 (>=0.12)
Requires-Dist: tqdm (>=4)
Requires-Dist: pandas (>=1.1)
Requires-Dist: numpy (>=1.20)
Requires-Dist: pybedtools (>=0.8)
